Workbook

Sheet Overview
A1: Topic
A2: Title | B2: Promise statement
A3: Think Like a CTO: Build, Buy or Partner? | B3: In 45 minutes, learn the 5 questions a CTO asks before building, buying or outsourcing any piece of tech.
B4: Include | C4: Exclude
A5: Experience | B5: 3–15 years of total experience (pilot: wider net) | C5: Freshers and students; job seekers
A6: Seniority | B6: SRE, DevOps, cloud, platform and backend engineers working on cloud, plus their leads and managers | C6: C-suite (reached separately through direct outreach)
A7: Company type | B7: Product and SaaS companies, GCCs, digital-first businesses (fintech, e-commerce, edtech, healthtech), in-house tech teams of enterprises (BFSI, healthcare, retail, manufacturing) | C7: AWS partners and cloud MSPs (competitors). IT-services / outsourcing firms: CEO decision
A8: Company size | B8: 50+ employees (existing MQL gate) | C8: Under 50 employees
A9: Geography | B9: India: Bengaluru, Hyderabad, Pune, Delhi-NCR, Chennai, Mumbai | C9: Outside India for this first episode
A10: Email | B10: Business email only | C10: Gmail, Yahoo, Outlook and other personal domains
A12: Platform | B12: How
A13: LinkedIn | B13: Paused for the pilot (₹2,500 per registration). Job title + years of experience (10–15) + seniority + company size 51+.
A14: Meta | B14: Age 24–45. Cloud/DevOps interests, developer interests, and Advantage+ with a lookalike of the email list.
A15: Own channels | B15: Existing email list and contacts,ceo/cto linkedin, employees sharing the invite.
A16: Youtube | B16: Demand Gen VSL ads: custom segments for Kubernetes, Terraform, AWS DevOps, SRE searches; Indian DevOps channels.
A17: Funnel stage | B17: Conservative
A18: Live attendees (expected from 200 registrations) | B18: =Funnel!B8 -> 50
A19: TNC Landing Page Best Practices: Video Clips, Speaker USPs, Tracking, and Retargeting
A21: Form Question in lead form : Need to discuss this----comapny mail id, name number
A22: date and time
A23: for eg : 29 oct Sat 11:00 AM
A25: Platform | B25: https://zoom.us/pricing
A26: Price | B26: INR 1580/- per user per month
A27: Duration / Participants | B27: 30 hours, 100 participants per meeting
A28: Recording | B28: Local & 10 GB cloud (per license)
A29: Mail | B29: Zoom Mail and Calendar in the Zoom app
A30: Clips | B30: Effortlessly create, edit, and share short videos. Stored clips are easily discoverable, boosting engagement / Unlimited

Sheet Topics
A1: Topic options (1 = weak, 5 = strong)
A2: Weights | C2: 0.3 | D2: 0.2 | E2: 0.25 | F2: 0.15 | G2: 0.1 | H2: =SUM(C2:G2) -> 1
A3: # | B3: Topic | C3: Audience pull | D3: Fits current deck | E3: Sales intel | F3: Not crowded | G3: Easy to prepare | H3: Score | I3: Promise to the attendee | J3: Who it pulls | K3: Speakers | L3: Main risk
A4: 1 | B4: Think Like a CTO: The Top-Down Lens for Tech Decisions | C4: 4 | D4: 5 | E4: 2 | F4: 4 | G4: 5 | H4: =ROUND(SUMPRODUCT(C4:G4,$C$2:$G$2),2) -> 3.8 | I4: Learn to see a business problem from 10,000 feet before you pick a tool. | J4: Managers who want to grow into leadership | K4: CEO + CTO | L4: Feels like a leadership talk; pulls career-advice seekers, not buyers
A5: 2 | B5: Build, Buy or Partner: How a CTO Decides What Not to Run In-House | C5: 4 | D5: 4 | E5: 5 | F5: 5 | G5: 4 | H5: =ROUND(SUMPRODUCT(C5:G5,$C$2:$G$2),2) -> 4.4 | I5: Get the 5 questions a CTO asks before building, buying or outsourcing anything. | J5: Managers who own vendors, cloud and team capacity | K5: CTO + CEO, optional customer guest | L5: Needs real examples, or it sounds like an MSP pitch
A6: 3 | B6: Your Cloud Bill, Read Like a CTO: A Live Bill Teardown | C6: 4 | D6: 3 | E6: 5 | F6: 4 | G6: 3 | H6: =ROUND(SUMPRODUCT(C6:G6,$C$2:$G$2),2) -> 3.95 | I6: See a real cloud bill taken apart live, and where the money leaks. | J6: DevOps, architects, anyone blamed for the bill | K6: CTO + cloud cost engineer | L6: Needs a real, anonymised bill with permission
A7: 4 | B7: Why AI Pilots Never Ship: The CTO's Path from POC to Production | C7: 5 | D7: 3 | E7: 3 | F7: 1 | G7: 3 | H7: =ROUND(SUMPRODUCT(C7:G7,$C$2:$G$2),2) -> 3.3 | I7: Why most AI pilots stall, and the CTO checklist to get one into production. | J7: Everyone; biggest pull of the five | K7: CTO + AI engineer | L7: Most crowded topic; attracts learners and job seekers
A8: 5 | B8: Who Touches Your Data? Vendor Risk and DPDP for Tech Leaders | C8: 3 | D8: 2 | E8: 4 | F8: 5 | G8: 2 | H8: =ROUND(SUMPRODUCT(C8:G8,$C$2:$G$2),2) -> 3.25 | I8: Map who handles your data, and what the DPDP Act makes you liable for. | J8: Heads of IT, security and compliance | K8: CTO + privacy lawyer | L8: Needs a lawyer on stage; Zarthi cannot give legal advice
A10: Title and promise options for Topic 2 (pick one of each)
B11: Title | C11: Promise statement
A12: A * | B12: Think Like a CTO: Build, Buy or Partner? | C12: In 45 minutes, learn the 5 questions a CTO asks before building, buying or outsourcing any piece of tech.
A13: B | B13: Own It or Hand It Off? The CTO's Decision Framework | C13: Walk away with a checklist for what your team should own, and what it should hand to a partner.
A14: C | B14: The Decisions That Make a CTO: Build vs. Buy vs. Partner | C14: Watch a CTO with 15 years of experience (ex-Microsoft) turn a real business problem into a build-or-partner call, step by step.

Sheet Audience
A1: Audience definition
B2: Include | C2: Exclude
A3: Experience | B3: 3–15 years of total experience (pilot: wider net) | C3: Freshers and people under 8 years; students; job seekers
A4: Seniority | B4: Hands-on engineers (SRE, DevOps, cloud, platform, backend developers) plus their leads and managers | C4: Students and freshers; C-suite (reached separately through direct outreach)
A5: Company type | B5: Product and SaaS companies, GCCs, digital-first businesses (fintech, e-commerce, edtech, healthtech), in-house tech teams of enterprises (BFSI, healthcare, retail, manufacturing) | C5: AWS partners and cloud MSPs (competitors). IT-services / outsourcing firms: CEO decision
A6: Company size | B6: 50+ employees (existing MQL gate) | C6: Under 50 employees
A7: Geography | B7: India: Bengaluru, Hyderabad, Pune, Delhi-NCR, Chennai, Mumbai, tier 2 cities | C7: Outside India for this first episode
A8: Email | B8: Pilot: any email, but company name is required (CEO decision 11) | C8: Gmail, Yahoo, Outlook and other personal domains
A10: Job titles to target
A11: Group | B11: Titles
A12: Engineering leadership | B12: Engineering Manager, Senior Engineering Manager, Associate Director – Engineering, Head of Engineering (mid-size companies)
A13: Architecture | B13: Solutions Architect, Cloud Architect, Technical Architect, Enterprise Architect, Principal / Staff Engineer
A14: Cloud and operations | B14: DevOps Lead / Manager, Platform Engineering Lead, SRE Manager, Head of Infrastructure, Cloud Operations Manager
A15: In-house IT | B15: IT Manager, Senior IT Manager, IT Infrastructure Manager, Deputy General Manager – IT
A16: Delivery and product | B16: Technical Program Manager, Delivery Head, Technology Product Manager
A17: Hands-on cloud engineers (pilot) | B17: SRE / Site Reliability Engineer, DevOps Engineer, Cloud Engineer, Platform Engineer, Infrastructure Engineer, Kubernetes Engineer, Backend / Software Developer working on AWS, Azure or GCP
A18: How we reach them
A19: Platform | B19: How
A20: LinkedIn | B20: Paused for the pilot (₹2,500 per registration). Targeting kept for later: job title + 10–15 years + seniority + company size 51+.
A21: Meta | B21: Age 24–45. 3 ad sets: cloud/DevOps interests, developer interests, Advantage+ with a 1% lookalike of the email list (Ads Plan tab).
A22: Own channels | B22: Existing email list and contacts, CEO and CTO LinkedIn posts, employees sharing the invite.
A23: YouTube | B23: Demand Gen: custom segments of people who searched Kubernetes, Terraform, AWS DevOps, SRE, CI/CD; Indian DevOps and cloud channels.
A24: Google Search | B24: Phrase + exact keywords on cloud architecture, DevOps/SRE best practices and build vs buy. Negatives for jobs and courses.
A25: Green = changed or added on 4-Oct.

Sheet Funnel
A1: Reverse funnel maths: 200 registrations (cream = assumptions)
A2: Updated 4-Oct: CEO asked for a mass audience for the pilot batch, so the target is now registrations, not live attendees.
A3: Funnel stage | B3: Pilot plan | C3: Why
A4: Registrations (target) | B4: 200 | C4: CEO target for the pilot batch.
A5: Buffer for fake / duplicate sign-ups | B5: 0.1 | C5: Mass audiences bring some junk entries; plan 10% extra.
A6: Registrations to plan for | B6: =ROUND(B4*(1+B5),0) -> 220 | C6: This is what the budget buys.
A7: Show-up rate | B7: 0.25 | C7: Same as the 22-Sep plan.
A8: Expected live attendees | B8: =ROUND(B4*B7,0) -> 50 | C8: From 200 real registrations. Zoom plan holds 100 per meeting.
A9: Landing page conversion | B9: 0.15 | C9: Same as the 22-Sep plan (VSL page visit → registration).
A10: Landing page visits needed | B10: =ROUND(B6/B9,0) -> 1467
A11: Ad click-through rate | B11: 0.006 | C11: Same as the 22-Sep plan. Video ads to a wide audience may do better.
A12: Impressions needed | B12: =ROUND(B10/B11,-2) -> 244500
A14: 22-Sep plan for comparison: 30 live, 150 registrations, ₹1,20,000 media.

Sheet Budget
A1: Budget for 200 registrations (pilot, mass audience)
A2: Cream = assumption. Meta and LinkedIn CPLs are from the 22-Sep plan; YouTube and Google Search are new estimates.
A3: Source | B3: Registrations | C3: Cost per registration | F3: Media budget (ex-GST) | K3: Notes
A4: Own email list + WhatsApp | B4: 15 | C4: 0 | F4: =B4*C4 -> 0 | K4: Free. Invite on Thu 8-Oct, reminder on 20-Oct.
A5: CEO/CTO LinkedIn posts + employee sharing | B5: 15 | C5: 0 | F5: =B5*C5 -> 0 | K5: Free. 2 posts each, every employee shares once.
A6: Meta: new audience (VSL page + instant-form test) | B6: 110 | C6: 700 | F6: =B6*C6 -> 77000 | K6: Main volume engine. ₹700 = your 22-Sep CPL. Wide audience (SRE, DevOps, cloud developers), age 24–45.
A7: Meta: retargeting (VSL viewers, page visitors) | B7: 15 | C7: 400 | F7: =B7*C7 -> 6000 | K7: People who watched 25%+ of the VSL or visited the page. Starts Wed 14-Oct. Estimate.
A8: YouTube: VSL video ads (in-stream, in-feed, Shorts) | B8: 35 | C8: 750 | F8: =B8*C8 -> 26250 | K8: Demand Gen campaign aimed at registrations. Estimate.
A9: Google Search | B9: 30 | C9: 950 | F9: =B9*C9 -> 28500 | K9: High intent but low search volume for webinar terms in India. Estimate.
A10: LinkedIn (Lead Gen Form) | B10: 0 | C10: 2500 | F10: =B10*C10 -> 0 | K10: Paused for the pilot: ₹2,500 per registration is too costly for a mass target. Type a number to switch it on.
A11: Total | B11: =SUM(B4:B10) -> 220 | C11: =IFERROR(F11/(B11-B4-B5),0) -> 725 | F11: =SUM(F4:F10) -> 137750 | K11: Cost per registration here = average across paid sources only.
A12: Check against the funnel | B12: =IF(B11>=Funnel!B6,"OK: covers "&Funnel!B6,"Short by "&(Funnel!B6-B11)) -> OK: covers 220
A14: Full budget
A15: Item | B15: Rate / qty | F15: Amount | K15: Notes
A16: Media (ex-GST) | F16: =F11 -> 137750 | K16: From the table above.
A17: GST on media | B17: 0.18 | F17: =F16*B17 -> 24795 | K17: 18% on Meta and Google invoices.
A18: Creative production (VSL, videos, statics, carousels) | F18: =Creatives!F38 -> 37000 | K18: Freelance editor + designer + basic kit. Breakdown at the bottom of the Creatives tab.
A19: Zoom licence (1 host, 1 month) | B19: 1580 | F19: =B19 -> 1580 | K19: Price from the Overview tab. Fine up to 100 live; upgrade if expected live goes above 100.
A20: Email + WhatsApp reminders (WhatsApp API messages) | B20: 5000 | F20: =B20 -> 5000 | K20: Estimate for ~220 people × 6 messages. Get a quote.
A21: Registration benefits (lucky draw) | F21: =Benefits!E14 -> 20000 | K21: From the Benefits tab.
A22: TOTAL (everything included) | F22: =SUM(F16:F21) -> 226125
A23: Cost per registration (everything included) | F23: =IFERROR(F22/Funnel!B4,0) -> 1130.625 | K23: 22-Sep plan: ₹1,41,600 with GST for 150 registrations, tools separate.
A24: Cost per expected live attendee | F24: =IFERROR(F22/Funnel!B8,0) -> 4522.5
A26: Released in three stages (ads run Fri 9-Oct to Mon 26-Oct)
A27: Stage | B27: Start | C27: End | D27: Days | E27: Share of media | F27: Media budget | G27: Per day | H27: Meta | I27: YouTube | J27: Google | K27: What happens | L27: Condition to move on
A28: 1. Test | B28: 46304 | C28: 46308 | D28: =C28-B28+1 -> 5 | E28: 0.2 | F28: =$F$11*E28 -> 27550 | G28: =IFERROR(F28/D28,0) -> 5510 | H28: =($F$6+$F$7+$F$10)*E28 -> 16600 | I28: =$F$8*E28 -> 5250 | J28: =$F$9*E28 -> 5700 | K28: 10 creatives live: 3 Meta ad sets × 3 creatives + YouTube VSL cut + Google Search. Find the cheapest hook. | L28: Meta ≤ ₹700, YouTube ≤ ₹900, Google ≤ ₹1,100 per registration. CEO review Tue 13-Oct.
A29: 2. Scale | B29: 46309 | C29: 46318 | D29: =C29-B29+1 -> 10 | E29: 0.68 | F29: =$F$11*E29 -> 93670 | G29: =IFERROR(F29/D29,0) -> 9367 | H29: =($F$6+$F$7+$F$10)*E29 -> 56440 | I29: =$F$8*E29 -> 17850 | J29: =$F$9*E29 -> 19380 | K29: Money behind winners only. Retargeting on. New creatives on 14, 18 and 21 Oct. | L29: Shift money every 2 days to the platform with the lowest cost per registration.
A30: 3. Last call | B30: 46319 | C30: 46321 | D30: =C30-B30+1 -> 3 | E30: 0.12 | F30: =$F$11*E30 -> 16530 | G30: =IFERROR(F30/D30,0) -> 5510 | H30: =($F$6+$F$7+$F$10)*E30 -> 9960 | I30: =$F$8*E30 -> 3150 | J30: =$F$9*E30 -> 3420 | K30: Countdown creatives to retargeting + best cold ad. Stop at 11:59 PM Mon 26-Oct. | L30: Stop the day before the webinar.
A31: Total | B31: =B28 -> 46304 | C31: =C30 -> 46321 | D31: =SUM(D28:D30) -> 18 | E31: =SUM(E28:E30) -> 1 | F31: =SUM(F28:F30) -> 137750 | G31: =IFERROR(F31/D31,0) -> 7652.7778 | H31: =SUM(H28:H30) -> 83000 | I31: =SUM(I28:I30) -> 26250 | J31: =SUM(J28:J30) -> 28500 | K31: =IF(ROUND(E31,4)=1,"OK","Shares must add to 100%") -> OK
A32: The Meta column includes LinkedIn spend if you switch LinkedIn back on.

Sheet Benefits
A1: Why register: benefits for registrants and live attendees
A2: Rule: the best rewards go to people who attend live, not to people who only register. This protects the show-up rate.
A3: # | B3: Benefit | C3: Who gets it | D3: When they get it | E3: Cost (₹) | F3: Where we say it | G3: Why engineers care
A4: 1 | B4: Send your build-or-buy question; the CTO answers the best ones live | C4: All registrants | D4: Question box on the form | E4: 0 | F4: Ad headline, VSL, form | G4: Free expert advice on their own real problem.
A5: 2 | B5: 1-page preview of the CTO's 5-question checklist | C5: All registrants | D5: Instantly, on the thank-you page | E5: 0 | F5: VSL, thank-you page | G5: Instant value, and it makes them want the full version.
A6: 3 | B6: Full 'Build, Buy or Partner' toolkit: 5-question checklist + decision template (PDF/Notion) | C6: Live attendees | D6: In the Zoom chat, last 10 minutes | E6: 0 | F6: Ads, VSL, reminders | G6: A tool they can use at work the next day.
A7: 4 | B7: Certificate of participation, signed by the CTO (LinkedIn-shareable) | C7: Live attendees who stay 40+ minutes | D7: Email within 24 hours | E7: 0 | F7: Ads (support line), VSL | G7: Shows on their LinkedIn profile and helps their career.
A8: 5 | B8: Slides and architecture templates from the session | C8: Live attendees | D8: Email within 24 hours | E8: 0 | F8: Reminders | G8: Saves them hours of making their own.
A9: 6 | B9: Free 30-minute 1:1 architecture or cloud review with a Zarthi engineer (10 slots) | C9: Live attendees from companies with 50+ staff | D9: Booking link at the end | E9: 0 | F9: VSL, last reminder | G9: Expert eyes on their own setup. This is also the sales pipeline.
A10: 7 | B10: Lucky draw: 10 × ₹1,000 + 2 × ₹5,000 vouchers | C10: People who stay till the end | D10: Drawn live in the last 5 minutes | E10: 20000 | F10: Ads (support line), reminders | G10: Small fun reason to stay till the end.
A11: 8 | B11: Join the 'Think Like a CTO' series community and get early access to episode 2 | C11: All registrants | D11: Thank-you page | E11: 0 | F11: Thank-you page | G11: Peer group of engineers growing into leadership.
A12: 9 | B12: Invite 2 teammates and your question jumps the queue | C12: Registrants who invite 2 colleagues | D12: Thank-you page share link | E12: 0 | F12: Thank-you page | G12: Free extra reach for us.
B14: Total cost | E14: =SUM(E4:E12) -> 20000
A16: Ad line to use
A17: Headline: "Build, buy or partner? Learn how a CTO decides, live and free."
A18: Support line: "CTO checklist + certificate + ₹5,000 lucky draw for live attendees."
A19: Do not promise a recording before the webinar: it lowers live attendance. Send it to no-shows afterwards.

Sheet Ads Plan
A1: Ads plan: Meta, YouTube and Google (LinkedIn paused for the pilot)
A2: Budgets and registrations are pulled from the Budget tab. Dates are from the stage table on the Budget tab.
A3: Platform | B3: Campaign | C3: Objective and bidding | D3: Targeting | E3: Placements | F3: Formats | G3: Creatives live | H3: Start | I3: End | J3: Media budget | K3: Per day (avg) | L3: Registrations | M3: Refresh / frequency
A4: Meta | B4: M1 Prospecting: Cloud & DevOps interests | C4: Leads, optimised for the 'Lead' event on the VSL page. Lowest cost. Week 1: one ad set also tests an instant form with the VSL. | D4: India: Bengaluru, Hyderabad, Pune, Delhi-NCR, Chennai, Mumbai + tier-2 cities. Age 24–45. Interests: AWS, Microsoft Azure, Google Cloud, DevOps, Kubernetes, Docker, Terraform, Site reliability engineering, Linux. Job titles where available: DevOps Engineer, SRE, Cloud Engineer, Platform Engineer. | E4: FB + IG Feed, Reels, Stories | F4: CTO 30s video, engineer POV reel, carousel C1, static S1/S2 | G4: 4 | H4: =Budget!B28 -> 46304 | I4: =Budget!C30 -> 46321 | J4: =Budget!F6*0.45 -> 34650 | K4: =IFERROR(J4/(I4-H4+1),0) -> 1925 | L4: =ROUND(Budget!B6*0.45,0) -> 50 | M4: New creative every 4–5 days. Swap when 7-day frequency > 2.5 or CTR drops 30%.
A5: Meta | B5: M2 Prospecting: Developers | C5: Same as M1. | D5: Same cities and age. Interests: GitHub, Stack Overflow, software development, Python, Java, Go, microservices, backend development. Excludes M1 audience. | E5: FB + IG Feed, Reels | F5: Myth vs fact reel, whiteboard video, carousel C2, static S3 | G5: 3 | H5: =Budget!B28 -> 46304 | I5: =Budget!C30 -> 46321 | J5: =Budget!F6*0.30 -> 23100 | K5: =IFERROR(J5/(I5-H5+1),0) -> 1283.3333 | L5: =ROUND(Budget!B6*0.30,0) -> 33 | M5: Same as M1.
A6: Meta | B6: M3 Prospecting: Advantage+ broad + lookalike | C6: Same as M1. Let Meta find people similar to the email list. | D6: 1% lookalike of the own email list and past webinar-style leads, plus Advantage+ audience with the M1 interests as suggestions. | E6: Advantage+ placements | F6: Best 3 creatives from M1/M2 after test week | G6: 3 | H6: =Budget!B28 -> 46304 | I6: =Budget!C30 -> 46321 | J6: =Budget!F6*0.25 -> 19250 | K6: =IFERROR(J6/(I6-H6+1),0) -> 1069.4444 | L6: =Budget!B6-L4-L5 -> 27 | M6: Fed with winners on 14, 18 and 21 Oct.
A7: Meta | B7: M4 Retargeting | C7: Leads, with a cost cap of ₹400. | D7: Watched 25%+ of the VSL or any video ad, visited the page but did not register (last 14 days), IG/FB engagers. Excludes people who registered. | E7: FB + IG Feed, Stories, Reels | F7: Benefits static, countdown static and video, social proof static | G7: 3 | H7: =Budget!B29 -> 46309 | I7: =Budget!C30 -> 46321 | J7: =Budget!F7 -> 6000 | K7: =IFERROR(J7/(I7-H7+1),0) -> 461.53846 | L7: =Budget!B7 -> 15 | M7: Countdown creative changes daily in the last 3 days.
A8: YouTube | B8: Y1 VSL video ads (Demand Gen) | C8: Demand Gen, optimised for registrations (maximise conversions). Switch to target CPA ₹750 after 15 registrations. | D8: India, age 24–45. Custom segments: people who searched Kubernetes, Terraform, AWS DevOps, SRE, platform engineering, CI/CD. Channel placements: Indian DevOps and cloud channels. Exclude kids/learning-only content. | E8: In-stream (skippable), in-feed, Shorts | F8: 60–90s VSL cut, 30s CTO video, 15s Shorts, 6s bumper (retargeting) | G8: 3 | H8: =Budget!B28 -> 46304 | I8: =Budget!C30 -> 46321 | J8: =Budget!F8 -> 26250 | K8: =IFERROR(J8/(I8-H8+1),0) -> 1458.3333 | L8: =Budget!B8 -> 35 | M8: New first 5 seconds (hook) every week. Bumper to VSL viewers from 21-Oct.
A9: Google | B9: G1 Search | C9: Search, maximise conversions. Switch to target CPA ₹950 after 15 registrations. | D9: 3 ad groups. (1) Cloud architecture: 'cloud architecture webinar', 'cloud architecture best practices'. (2) DevOps/SRE: 'devops webinar', 'sre best practices', 'platform engineering'. (3) Build vs buy: 'build vs buy software', 'in-house vs outsourcing devops'. Phrase + exact. Negatives: jobs, salary, course, certification, interview, training institute, free download. | E9: Google Search only (no Display) | F9: 3 responsive search ads + sitelinks (Agenda, Speakers, Register) | G9: 3 | H9: =Budget!B28 -> 46304 | I9: =Budget!C30 -> 46321 | J9: =Budget!F9 -> 28500 | K9: =IFERROR(J9/(I9-H9+1),0) -> 1583.3333 | L9: =Budget!B9 -> 30 | M9: Check search terms every 2 days, add negatives.
A10: LinkedIn | B10: L1 Lead Gen Form (paused) | C10: Paused for the pilot. | D10: Job titles from the Audience tab, 10–15 years experience, company size 51+. | E10: Feed | F10: Speaker card, document ad | G10: 0 | H10: =Budget!B28 -> 46304 | I10: =Budget!C30 -> 46321 | J10: =Budget!F10 -> 0 | K10: =IFERROR(J10/(I10-H10+1),0) -> 0 | L10: =Budget!B10 -> 0 | M10: Switch on via the Budget tab if the CEO wants senior-only reach.
A11: Total | G11: =SUM(G4:G10) -> 19 | J11: =SUM(J4:J10) -> 137750 | K11: =SUM(K4:K10) -> 7780.9829 | L11: =SUM(L4:L10) -> 190
A12: M1–M3 split Meta's new-audience budget 45% / 30% / 25%. Totals match the paid rows on the Budget tab.
A14: How often we check and change things
A15: When | B15: What | D15: Rule
A16: Every day, 10 AM | B16: Check cost per registration, CTR and frequency for every ad | D16: Pause any ad over 1.5× the target CPL after spending 2× the target CPL.
A17: Every 2 days | B17: Move money between ad sets and platforms; add Google negative keywords | D17: Move money to the lowest cost per registration.
A18: Every 4–5 days (14, 18, 21 Oct) | B18: Add 3 new creatives (new hooks on winning formats) | D18: Keep 3–4 ads per ad set; never more than 6.
A19: Every Monday | B19: Registration count and spend to CEO (12, 19, 26 Oct) | D19: Use the Daily Plan tab as the target.
A20: Tue 13-Oct | B20: Test review with CEO | D20: Release the scale budget only if test gates pass (Budget tab).
A21: Sat 24-Oct | B21: Switch to countdown creatives | D21: Retargeting gets 60% of the last-call budget.

Sheet Creatives
A1: Creative plan: videos, statics and carousels
A2: Creative is the main lever for a mass audience. One 2-hour shoot on Mon 5 or Tue 6 Oct produces all the videos.
A3: ID | B3: Creative | C3: Format and length | D3: Size / ratio | E3: Platform | F3: Audience stage | G3: Hook (first 3 seconds / headline) | H3: What it shows | I3: Who | J3: Ready by | K3: First live
A4: V1 | B4: Main VSL (landing page video) | C4: Video, 3–4 min | D4: 16:9 | E4: VSL page, YouTube retargeting | F4: Warm | G4: "Every engineer gets asked one day: should we build this, buy it, or hand it off? Here's how a CTO decides." | H4: Full script on the VSL Funnel tab. CTO on camera, CEO intro, 1 of the 5 questions taught in full. | I4: CTO + CEO | J4: 46303 | K4: 46304
A5: V2 | B5: YouTube VSL cut | C5: Video, 60–90 s, skippable | D5: 16:9 | E5: YouTube in-stream / in-feed | F5: Cold | G5: "SRE or DevOps engineer? You've been asked to build something you should have bought." | H5: Hook, 1 real example, the promise of 5 questions, date, register CTA. Name and face in the first 5 seconds. | I5: CTO | J5: 46303 | K5: 46304
A6: V3 | B6: CTO talking head | C6: Video, 30 s | D6: 9:16 + 4:5 | E6: Meta Reels / Feed | F6: Cold | G6: "15 years, ex-Microsoft. The #1 mistake I see engineers make when they pick a tool." | H6: One mistake, why it costs, invite to the live session. Burned-in captions. | I6: CTO | J6: 46303 | K6: 46304
A7: V4 | B7: CEO talking head | C7: Video, 30 s | D7: 4:5 | E7: Meta Feed | F7: Cold | G7: "Our best engineers think like CTOs. Here's the one habit they share." | H7: Habit, why it matters for their career, invite. | I7: CEO | J7: 46303 | K7: 46304
A8: V5 | B8: Myth vs fact reel | C8: Video, 15 s, text on screen | D8: 9:16 | E8: IG Reels, YouTube Shorts | F8: Cold | G8: "Myth: building it in-house is always cheaper." | H8: 3 quick myth/fact cards over b-roll of dashboards and code, end card with date. | I8: Editor | J8: 46303 | K8: 46304
A9: V6 | B9: Whiteboard explainer | C9: Video, 45 s | D9: 9:16 + 16:9 | E9: Meta, YouTube | F9: Cold | G9: "Build, buy or partner: here's the 2×2 a CTO draws first." | H9: CTO draws the matrix on a whiteboard or iPad and places 3 examples (CI/CD, monitoring, data platform). | I9: CTO | J9: 46303 | K9: 46309
A10: V7 | B10: Engineer POV (selfie style) | C10: Video, 20–30 s | D10: 9:16 | E10: Meta Reels, Shorts | F10: Cold | G10: "I was the DevOps guy who said 'we'll just build it'. Six months later…" | H10: A Zarthi engineer tells a true short story, phone-shot, natural light. Feels native, not like an ad. | I10: Zarthi engineer | J10: 46308 | K10: 46309
A11: V8 | B11: CEO + CTO podcast clip | C11: Video, 30–45 s | D11: 1:1 + 9:16 | E11: Meta, YouTube | F11: Cold / warm | G11: CEO: "Would you let your team build its own monitoring stack?" CTO: "Only if…" | H11: Two-person conversation clip cut from the shoot. Captions on. | I11: CEO + CTO | J11: 46308 | K11: 46313
A12: V9 | B12: YouTube bumper | C12: Video, 6 s, non-skippable | D12: 16:9 | E12: YouTube retargeting | F12: Warm | G12: "Build, buy or partner? Free CTO session, Tue 27 Oct, 4 PM." | H12: Logo-free, speaker face, date, CTA. | I12: Editor | J12: 46313 | K12: 46316
A13: V10 | B13: Countdown video | C13: Video, 10 s, 3 versions | D13: 9:16 + 4:5 | E13: Meta + YouTube retargeting | F13: Hot | G13: "3 days left" / "Tomorrow, 4 PM" / "Today, 4 PM: join link inside" | H13: Speaker face, seats-left line (Zoom holds 100), CTA. | I13: Editor | J13: 46317 | K13: 46319
A14: S1 | B14: Speaker card | C14: Static | D14: 1080×1350, 1080×1920 | E14: Meta, YouTube Demand Gen | F14: Cold | G14: "Think Like a CTO: Build, Buy or Partner?" | H14: CTO + CEO photos, credentials, date, 'Free live session'. | I14: Designer | J14: 46302 | K14: 46304
A15: S2 | B15: Question hook | C15: Static | D15: 1080×1350 | E15: Meta | F15: Cold | G15: "Would you build your own monitoring stack in 2026?" | H15: Big question, small answer line: 'A CTO asks 5 questions first. Learn them live.' | I15: Designer | J15: 46302 | K15: 46304
... A23: G1 | B23: Google search ads | C23: Text: 15 headlines, 4 descriptions per ad group | D23: - | E23: Google Search | F23: Intent | G23: "Free CTO Webinar, 27 Oct" | "Build, Buy or Partner?" | "For SRE & DevOps Engineers" | H23: 3 ad groups (see Ads Plan). Sitelinks: Agenda, Speakers, Benefits, Register. | I23: Shourya | J23: 46302 | K23: 46304
A24: Counts: | B24: =COUNTIF(A4:A23,"V*")&" videos, "&COUNTIF(A4:A23,"S*")&" statics, "&COUNTIF(A4:A23,"C*")&" carousels, "&COUNTIF(A4:A23,"G*")&" text ad set" -> 10 videos, 6 statics, 3 carousels, 1 text ad set
A26: Creative release calendar
B27: Date | C27: Batch | G27: What goes live
B28: 46304 | C28: Launch (test) | G28: V1, V2, V3, V4, V5, S1, S2, S3, C1, G1: 10 creatives across 3 platforms
B29: 46309 | C29: Refresh 1 | G29: V6, V7, S4, C2 + pause the bottom 30%
B30: 46313 | C30: Refresh 2 | G30: V8, S6, C3 + new hooks on the best video
B31: 46316 | C31: Refresh 3 | G31: V9 bumper + 2 new hook versions of the top 2 ads
B32: 46319 | C32: Last call | G32: V10 and S5 countdowns, retargeting-heavy
A33: Production cost (estimates; get quotes)
B34: Item | C34: Qty | D34: Rate (₹) | F34: Cost (₹)
B35: Freelance video editor: VSL + 9 short videos + versions | C35: 1 | D35: 20000 | F35: =C35*D35 -> 20000
B36: Freelance designer: 6 statics + 3 carousels in all sizes | C36: 1 | D36: 10000 | F36: =C36*D36 -> 10000
B37: Lapel mic + ring light (one-time, reused for the series) | C37: 1 | D37: 7000 | F37: =C37*D37 -> 7000
B38: Total production | F38: =SUM(F35:F37) -> 37000
A39: Every video gets burned-in captions: most people watch Reels and Shorts with the sound off.

Sheet VSL Funnel
A1: VSL funnel: from ad to booked call
A2: VSL = video sales letter: a 3–4 minute video at the top of the landing page that sells the webinar.
A3: # | B3: Step | C3: What the person sees or does | D3: Rate | E3: People | F3: Tool / note
A4: 1 | B4: Sees an ad | C4: Video, static or carousel from the Creatives tab | E4: =Funnel!B12 -> 244500 | F4: Meta, YouTube, Google
A5: 2 | B5: Clicks to the VSL page | C5: Landing page with the VSL on top | D5: =Funnel!B11 -> 0.006 | E5: =Funnel!B10 -> 1467 | F5: Rate = ad click-through rate
A6: 3 | B6: Presses play on the VSL | C6: Autoplay muted with captions, big play button | D6: 0.6 | E6: =ROUND(E5*D6,0) -> 880 | F6: Estimate
A7: 4 | B7: Watches 50%+ of the VSL | C7: Reaches the 'what you get' section | D7: 0.45 | E7: =ROUND(E6*D7,0) -> 396 | F7: Estimate. Meta/YouTube retarget everyone from here.
A8: 5 | B8: Registers | C8: 5-field form below the video and repeated at the end | D8: =Funnel!B9 -> 0.15 | E8: =ROUND(E5*D8,0) -> 220 | F8: Rate = landing page conversion (of all page visitors)
A9: 6 | B9: Thank-you page actions | C9: Adds to calendar, opts in to WhatsApp, invites 2 teammates | D9: 0.6 | E9: =ROUND(E8*D9,0) -> 132 | F9: Estimate: people who add it to their calendar
A10: 7 | B10: Attends live | C10: Reminders from the table below | D10: =Funnel!B7 -> 0.25 | E10: =ROUND(Funnel!B4*D10,0) -> 50 | F10: Based on the 200 real registrations
A11: 8 | B11: Stays till the end | C11: Lucky draw and toolkit in the last 10 minutes | D11: 0.65 | E11: =ROUND(E10*D11,0) -> 33 | F11: Estimate
A12: 9 | B12: Books a free 1:1 review | C12: Booking link in chat and in the thank-you email | D12: 0.12 | E12: =ROUND(E11*D12,0) -> 4 | F12: Estimate
A14: VSL script (3–4 minutes, recorded on Mon 5 or Tue 6 Oct)
B15: Time | C15: Section | F15: What to say / show
B16: 0:00–0:15 | C16: Hook | F16: "Every engineer gets asked one day: should we build this, buy it, or hand it off? Get it wrong and you own it for years. Here's how a CTO decides."
B17: 0:15–0:45 | C17: The problem | F17: Real pain: building a monitoring stack no one maintains, buying a tool that doesn't fit, being blamed for the cloud bill. 'You're expected to decide like a CTO, but nobody taught you how.'
B18: 0:45–1:15 | C18: Who we are | F18: CTO: 15 years, ex-Microsoft, examples of decisions made. CEO: why Zarthi runs this series. Show faces and logos of real projects (with permission).
B19: 1:15–2:00 | C19: Free value | F19: Teach question 1 of the 5 in full, with one quick example. Proof the session is useful, not a sales pitch.
B20: 2:00–2:40 | C20: What you get live | F20: The other 4 questions, a live real-world case, your own question answered, plus the toolkit, certificate and lucky draw (Benefits tab).
B21: 2:40–3:10 | C21: Who it's for / not for | F21: For: SRE, DevOps, cloud and backend engineers and their leads. Not for: people looking for a beginner course or a job.
B22: 3:10–3:30 | C22: Call to action | F22: "Tuesday 27 October, 4 PM, 45 minutes, free. Zoom holds 100 people live, so register below now."
A24: Landing page, top to bottom
A25: 1. Headline = the title. Sub-headline = the promise. Date, time and 'Free' visible without scrolling.
A26: 2. The VSL (V1), autoplay muted with captions.
A27: 3. Form right under the video: name, work or personal email, phone, job title, company. Plus 'Your build-or-buy question' (optional).
A28: 4. 'What you get' with the benefits, then speaker bios, then agenda (45 min + Q&A).
A29: 5. 'Who it's for' block, then the form repeated at the bottom. No menu or links that take people away.
A30: 6. Tracking: Meta Pixel 'Lead', Google Ads conversion, YouTube conversion and UTMs fire only on a real form submit.
A32: Reminder sequence (free; this decides the show-up rate)
B33: When | C33: Channel | F33: Message
B34: Right after registering | C34: Email + WhatsApp | F34: Confirmation, calendar invite, checklist preview, 'send your question' link
B35: Tue 20-Oct (7 days before) | C35: Email | F35: Teaser: question 1 recap + 'the other 4 are live only'
B36: Sat 24-Oct (3 days before) | C36: Email | F36: 'Your question may be picked' + agenda
B37: Mon 26-Oct (1 day before) | C37: Email + WhatsApp | F37: Tomorrow at 4 PM + reminder of the lucky draw and certificate
B38: Tue 27-Oct, 3:00 PM (1 hour before) | C38: Email + WhatsApp | F38: Join link (the same link every time)
B39: Tue 27-Oct, 3:55 PM | C39: WhatsApp | F39: 'We're going live in 5 minutes'
B40: Tue 27-Oct, 4:05 PM | C40: Email + WhatsApp | F40: To people who haven't joined: 'We've started, the live case is at the end'
B41: Tue 27-Oct evening | C41: Email | F41: Attendees: certificate, toolkit, booking link. No-shows: recording + booking link.

Sheet Daily Plan
A1: Daily plan: spend and registration target, 9-Oct to 26-Oct
A2: Spend per day comes from the stage table on the Budget tab. Use 'Registrations by today' as the daily target.
A3: Date | B3: Stage | C3: Meta (₹) | D3: YouTube (₹) | E3: Google (₹) | F3: Total (₹) | G3: Spend so far (₹) | H3: Registrations by today | I3: Creative action | J3: Review / other
A4: 46304 | B4: =IF(A4<=Budget!$C$28,"Test",IF(A4<=Budget!$C$29,"Scale","Last call")) -> Test | C4: =IF(A4<=Budget!$C$28,Budget!$H$28/Budget!$D$28,IF(A4<=Budget!$C$29,Budget!$H$29/Budget!$D$29,Budget!$H$30/Budget!$D$30)) -> 3320 | D4: =IF(A4<=Budget!$C$28,Budget!$I$28/Budget!$D$28,IF(A4<=Budget!$C$29,Budget!$I$29/Budget!$D$29,Budget!$I$30/Budget!$D$30)) -> 1050 | E4: =IF(A4<=Budget!$C$28,Budget!$J$28/Budget!$D$28,IF(A4<=Budget!$C$29,Budget!$J$29/Budget!$D$29,Budget!$J$30/Budget!$D$30)) -> 1140 | F4: =SUM(C4:E4) -> 5510 | G4: =SUM($F$4:F4) -> 5510 | H4: =ROUND(Budget!$B$4+Budget!$B$5+(Budget!$B$11-Budget!$B$4-Budget!$B$5)*G4/Budget!$F$11,0) -> 38 | I4: Launch 10 creatives (test batch) | J4: Paid ads start. Own email invite went out Thu 8-Oct.
A5: 46305 | B5: =IF(A5<=Budget!$C$28,"Test",IF(A5<=Budget!$C$29,"Scale","Last call")) -> Test | C5: =IF(A5<=Budget!$C$28,Budget!$H$28/Budget!$D$28,IF(A5<=Budget!$C$29,Budget!$H$29/Budget!$D$29,Budget!$H$30/Budget!$D$30)) -> 3320 | D5: =IF(A5<=Budget!$C$28,Budget!$I$28/Budget!$D$28,IF(A5<=Budget!$C$29,Budget!$I$29/Budget!$D$29,Budget!$I$30/Budget!$D$30)) -> 1050 | E5: =IF(A5<=Budget!$C$28,Budget!$J$28/Budget!$D$28,IF(A5<=Budget!$C$29,Budget!$J$29/Budget!$D$29,Budget!$J$30/Budget!$D$30)) -> 1140 | F5: =SUM(C5:E5) -> 5510 | G5: =SUM($F$4:F5) -> 11020 | H5: =ROUND(Budget!$B$4+Budget!$B$5+(Budget!$B$11-Budget!$B$4-Budget!$B$5)*G5/Budget!$F$11,0) -> 45
A6: 46306 | B6: =IF(A6<=Budget!$C$28,"Test",IF(A6<=Budget!$C$29,"Scale","Last call")) -> Test | C6: =IF(A6<=Budget!$C$28,Budget!$H$28/Budget!$D$28,IF(A6<=Budget!$C$29,Budget!$H$29/Budget!$D$29,Budget!$H$30/Budget!$D$30)) -> 3320 | D6: =IF(A6<=Budget!$C$28,Budget!$I$28/Budget!$D$28,IF(A6<=Budget!$C$29,Budget!$I$29/Budget!$D$29,Budget!$I$30/Budget!$D$30)) -> 1050 | E6: =IF(A6<=Budget!$C$28,Budget!$J$28/Budget!$D$28,IF(A6<=Budget!$C$29,Budget!$J$29/Budget!$D$29,Budget!$J$30/Budget!$D$30)) -> 1140 | F6: =SUM(C6:E6) -> 5510 | G6: =SUM($F$4:F6) -> 16530 | H6: =ROUND(Budget!$B$4+Budget!$B$5+(Budget!$B$11-Budget!$B$4-Budget!$B$5)*G6/Budget!$F$11,0) -> 53
A7: 46307 | B7: =IF(A7<=Budget!$C$28,"Test",IF(A7<=Budget!$C$29,"Scale","Last call")) -> Test | C7: =IF(A7<=Budget!$C$28,Budget!$H$28/Budget!$D$28,IF(A7<=Budget!$C$29,Budget!$H$29/Budget!$D$29,Budget!$H$30/Budget!$D$30)) -> 3320 | D7: =IF(A7<=Budget!$C$28,Budget!$I$28/Budget!$D$28,IF(A7<=Budget!$C$29,Budget!$I$29/Budget!$D$29,Budget!$I$30/Budget!$D$30)) -> 1050 | E7: =IF(A7<=Budget!$C$28,Budget!$J$28/Budget!$D$28,IF(A7<=Budget!$C$29,Budget!$J$29/Budget!$D$29,Budget!$J$30/Budget!$D$30)) -> 1140 | F7: =SUM(C7:E7) -> 5510 | G7: =SUM($F$4:F7) -> 22040 | H7: =ROUND(Budget!$B$4+Budget!$B$5+(Budget!$B$11-Budget!$B$4-Budget!$B$5)*G7/Budget!$F$11,0) -> 60 | J7: Monday update to CEO
A8: 46308 | B8: =IF(A8<=Budget!$C$28,"Test",IF(A8<=Budget!$C$29,"Scale","Last call")) -> Test | C8: =IF(A8<=Budget!$C$28,Budget!$H$28/Budget!$D$28,IF(A8<=Budget!$C$29,Budget!$H$29/Budget!$D$29,Budget!$H$30/Budget!$D$30)) -> 3320 | D8: =IF(A8<=Budget!$C$28,Budget!$I$28/Budget!$D$28,IF(A8<=Budget!$C$29,Budget!$I$29/Budget!$D$29,Budget!$I$30/Budget!$D$30)) -> 1050 | E8: =IF(A8<=Budget!$C$28,Budget!$J$28/Budget!$D$28,IF(A8<=Budget!$C$29,Budget!$J$29/Budget!$D$29,Budget!$J$30/Budget!$D$30)) -> 1140 | F8: =SUM(C8:E8) -> 5510 | G8: =SUM($F$4:F8) -> 27550 | H8: =ROUND(Budget!$B$4+Budget!$B$5+(Budget!$B$11-Budget!$B$4-Budget!$B$5)*G8/Budget!$F$11,0) -> 68 | I8: Pause losers | J8: Test review with CEO: release scale budget?
A9: 46309 | B9: =IF(A9<=Budget!$C$28,"Test",IF(A9<=Budget!$C$29,"Scale","Last call")) -> Scale | C9: =IF(A9<=Budget!$C$28,Budget!$H$28/Budget!$D$28,IF(A9<=Budget!$C$29,Budget!$H$29/Budget!$D$29,Budget!$H$30/Budget!$D$30)) -> 5644 | D9: =IF(A9<=Budget!$C$28,Budget!$I$28/Budget!$D$28,IF(A9<=Budget!$C$29,Budget!$I$29/Budget!$D$29,Budget!$I$30/Budget!$D$30)) -> 1785 | E9: =IF(A9<=Budget!$C$28,Budget!$J$28/Budget!$D$28,IF(A9<=Budget!$C$29,Budget!$J$29/Budget!$D$29,Budget!$J$30/Budget!$D$30)) -> 1938 | F9: =SUM(C9:E9) -> 9367 | G9: =SUM($F$4:F9) -> 36917 | H9: =ROUND(Budget!$B$4+Budget!$B$5+(Budget!$B$11-Budget!$B$4-Budget!$B$5)*G9/Budget!$F$11,0) -> 81 | I9: Refresh 1: V6, V7, S4, C2 | J9: Retargeting (M4) starts
A10: 46310 | B10: =IF(A10<=Budget!$C$28,"Test",IF(A10<=Budget!$C$29,"Scale","Last call")) -> Scale | C10: =IF(A10<=Budget!$C$28,Budget!$H$28/Budget!$D$28,IF(A10<=Budget!$C$29,Budget!$H$29/Budget!$D$29,Budget!$H$30/Budget!$D$30)) -> 5644 | D10: =IF(A10<=Budget!$C$28,Budget!$I$28/Budget!$D$28,IF(A10<=Budget!$C$29,Budget!$I$29/Budget!$D$29,Budget!$I$30/Budget!$D$30)) -> 1785 | E10: =IF(A10<=Budget!$C$28,Budget!$J$28/Budget!$D$28,IF(A10<=Budget!$C$29,Budget!$J$29/Budget!$D$29,Budget!$J$30/Budget!$D$30)) -> 1938 | F10: =SUM(C10:E10) -> 9367 | G10: =SUM($F$4:F10) -> 46284 | H10: =ROUND(Budget!$B$4+Budget!$B$5+(Budget!$B$11-Budget!$B$4-Budget!$B$5)*G10/Budget!$F$11,0) -> 94
A11: 46311 | B11: =IF(A11<=Budget!$C$28,"Test",IF(A11<=Budget!$C$29,"Scale","Last call")) -> Scale | C11: =IF(A11<=Budget!$C$28,Budget!$H$28/Budget!$D$28,IF(A11<=Budget!$C$29,Budget!$H$29/Budget!$D$29,Budget!$H$30/Budget!$D$30)) -> 5644 | D11: =IF(A11<=Budget!$C$28,Budget!$I$28/Budget!$D$28,IF(A11<=Budget!$C$29,Budget!$I$29/Budget!$D$29,Budget!$I$30/Budget!$D$30)) -> 1785 | E11: =IF(A11<=Budget!$C$28,Budget!$J$28/Budget!$D$28,IF(A11<=Budget!$C$29,Budget!$J$29/Budget!$D$29,Budget!$J$30/Budget!$D$30)) -> 1938 | F11: =SUM(C11:E11) -> 9367 | G11: =SUM($F$4:F11) -> 55651 | H11: =ROUND(Budget!$B$4+Budget!$B$5+(Budget!$B$11-Budget!$B$4-Budget!$B$5)*G11/Budget!$F$11,0) -> 107
A12: 46312 | B12: =IF(A12<=Budget!$C$28,"Test",IF(A12<=Budget!$C$29,"Scale","Last call")) -> Scale | C12: =IF(A12<=Budget!$C$28,Budget!$H$28/Budget!$D$28,IF(A12<=Budget!$C$29,Budget!$H$29/Budget!$D$29,Budget!$H$30/Budget!$D$30)) -> 5644 | D12: =IF(A12<=Budget!$C$28,Budget!$I$28/Budget!$D$28,IF(A12<=Budget!$C$29,Budget!$I$29/Budget!$D$29,Budget!$I$30/Budget!$D$30)) -> 1785 | E12: =IF(A12<=Budget!$C$28,Budget!$J$28/Budget!$D$28,IF(A12<=Budget!$C$29,Budget!$J$29/Budget!$D$29,Budget!$J$30/Budget!$D$30)) -> 1938 | F12: =SUM(C12:E12) -> 9367 | G12: =SUM($F$4:F12) -> 65018 | H12: =ROUND(Budget!$B$4+Budget!$B$5+(Budget!$B$11-Budget!$B$4-Budget!$B$5)*G12/Budget!$F$11,0) -> 120
A13: 46313 | B13: =IF(A13<=Budget!$C$28,"Test",IF(A13<=Budget!$C$29,"Scale","Last call")) -> Scale | C13: =IF(A13<=Budget!$C$28,Budget!$H$28/Budget!$D$28,IF(A13<=Budget!$C$29,Budget!$H$29/Budget!$D$29,Budget!$H$30/Budget!$D$30)) -> 5644 | D13: =IF(A13<=Budget!$C$28,Budget!$I$28/Budget!$D$28,IF(A13<=Budget!$C$29,Budget!$I$29/Budget!$D$29,Budget!$I$30/Budget!$D$30)) -> 1785 | E13: =IF(A13<=Budget!$C$28,Budget!$J$28/Budget!$D$28,IF(A13<=Budget!$C$29,Budget!$J$29/Budget!$D$29,Budget!$J$30/Budget!$D$30)) -> 1938 | F13: =SUM(C13:E13) -> 9367 | G13: =SUM($F$4:F13) -> 74385 | H13: =ROUND(Budget!$B$4+Budget!$B$5+(Budget!$B$11-Budget!$B$4-Budget!$B$5)*G13/Budget!$F$11,0) -> 133 | I13: Refresh 2: V8, S6, C3
A14: 46314 | B14: =IF(A14<=Budget!$C$28,"Test",IF(A14<=Budget!$C$29,"Scale","Last call")) -> Scale | C14: =IF(A14<=Budget!$C$28,Budget!$H$28/Budget!$D$28,IF(A14<=Budget!$C$29,Budget!$H$29/Budget!$D$29,Budget!$H$30/Budget!$D$30)) -> 5644 | D14: =IF(A14<=Budget!$C$28,Budget!$I$28/Budget!$D$28,IF(A14<=Budget!$C$29,Budget!$I$29/Budget!$D$29,Budget!$I$30/Budget!$D$30)) -> 1785 | E14: =IF(A14<=Budget!$C$28,Budget!$J$28/Budget!$D$28,IF(A14<=Budget!$C$29,Budget!$J$29/Budget!$D$29,Budget!$J$30/Budget!$D$30)) -> 1938 | F14: =SUM(C14:E14) -> 9367 | G14: =SUM($F$4:F14) -> 83752 | H14: =ROUND(Budget!$B$4+Budget!$B$5+(Budget!$B$11-Budget!$B$4-Budget!$B$5)*G14/Budget!$F$11,0) -> 146 | J14: Monday update to CEO
A15: 46315 | B15: =IF(A15<=Budget!$C$28,"Test",IF(A15<=Budget!$C$29,"Scale","Last call")) -> Scale | C15: =IF(A15<=Budget!$C$28,Budget!$H$28/Budget!$D$28,IF(A15<=Budget!$C$29,Budget!$H$29/Budget!$D$29,Budget!$H$30/Budget!$D$30)) -> 5644 | D15: =IF(A15<=Budget!$C$28,Budget!$I$28/Budget!$D$28,IF(A15<=Budget!$C$29,Budget!$I$29/Budget!$D$29,Budget!$I$30/Budget!$D$30)) -> 1785 | E15: =IF(A15<=Budget!$C$28,Budget!$J$28/Budget!$D$28,IF(A15<=Budget!$C$29,Budget!$J$29/Budget!$D$29,Budget!$J$30/Budget!$D$30)) -> 1938 | F15: =SUM(C15:E15) -> 9367 | G15: =SUM($F$4:F15) -> 93119 | H15: =ROUND(Budget!$B$4+Budget!$B$5+(Budget!$B$11-Budget!$B$4-Budget!$B$5)*G15/Budget!$F$11,0) -> 158 | J15: 7-day reminder email; email list reminder
A16: 46316 | B16: =IF(A16<=Budget!$C$28,"Test",IF(A16<=Budget!$C$29,"Scale","Last call")) -> Scale | C16: =IF(A16<=Budget!$C$28,Budget!$H$28/Budget!$D$28,IF(A16<=Budget!$C$29,Budget!$H$29/Budget!$D$29,Budget!$H$30/Budget!$D$30)) -> 5644 | D16: =IF(A16<=Budget!$C$28,Budget!$I$28/Budget!$D$28,IF(A16<=Budget!$C$29,Budget!$I$29/Budget!$D$29,Budget!$I$30/Budget!$D$30)) -> 1785 | E16: =IF(A16<=Budget!$C$28,Budget!$J$28/Budget!$D$28,IF(A16<=Budget!$C$29,Budget!$J$29/Budget!$D$29,Budget!$J$30/Budget!$D$30)) -> 1938 | F16: =SUM(C16:E16) -> 9367 | G16: =SUM($F$4:F16) -> 102486 | H16: =ROUND(Budget!$B$4+Budget!$B$5+(Budget!$B$11-Budget!$B$4-Budget!$B$5)*G16/Budget!$F$11,0) -> 171 | I16: Refresh 3: V9 bumper + new hooks
A17: 46317 | B17: =IF(A17<=Budget!$C$28,"Test",IF(A17<=Budget!$C$29,"Scale","Last call")) -> Scale | C17: =IF(A17<=Budget!$C$28,Budget!$H$28/Budget!$D$28,IF(A17<=Budget!$C$29,Budget!$H$29/Budget!$D$29,Budget!$H$30/Budget!$D$30)) -> 5644 | D17: =IF(A17<=Budget!$C$28,Budget!$I$28/Budget!$D$28,IF(A17<=Budget!$C$29,Budget!$I$29/Budget!$D$29,Budget!$I$30/Budget!$D$30)) -> 1785 | E17: =IF(A17<=Budget!$C$28,Budget!$J$28/Budget!$D$28,IF(A17<=Budget!$C$29,Budget!$J$29/Budget!$D$29,Budget!$J$30/Budget!$D$30)) -> 1938 | F17: =SUM(C17:E17) -> 9367 | G17: =SUM($F$4:F17) -> 111853 | H17: =ROUND(Budget!$B$4+Budget!$B$5+(Budget!$B$11-Budget!$B$4-Budget!$B$5)*G17/Budget!$F$11,0) -> 184
A18: 46318 | B18: =IF(A18<=Budget!$C$28,"Test",IF(A18<=Budget!$C$29,"Scale","Last call")) -> Scale | C18: =IF(A18<=Budget!$C$28,Budget!$H$28/Budget!$D$28,IF(A18<=Budget!$C$29,Budget!$H$29/Budget!$D$29,Budget!$H$30/Budget!$D$30)) -> 5644 | D18: =IF(A18<=Budget!$C$28,Budget!$I$28/Budget!$D$28,IF(A18<=Budget!$C$29,Budget!$I$29/Budget!$D$29,Budget!$I$30/Budget!$D$30)) -> 1785 | E18: =IF(A18<=Budget!$C$28,Budget!$J$28/Budget!$D$28,IF(A18<=Budget!$C$29,Budget!$J$29/Budget!$D$29,Budget!$J$30/Budget!$D$30)) -> 1938 | F18: =SUM(C18:E18) -> 9367 | G18: =SUM($F$4:F18) -> 121220 | H18: =ROUND(Budget!$B$4+Budget!$B$5+(Budget!$B$11-Budget!$B$4-Budget!$B$5)*G18/Budget!$F$11,0) -> 197 | J18: Mock call (deck, audio, screen share)
A19: 46319 | B19: =IF(A19<=Budget!$C$28,"Test",IF(A19<=Budget!$C$29,"Scale","Last call")) -> Last call | C19: =IF(A19<=Budget!$C$28,Budget!$H$28/Budget!$D$28,IF(A19<=Budget!$C$29,Budget!$H$29/Budget!$D$29,Budget!$H$30/Budget!$D$30)) -> 3320 | D19: =IF(A19<=Budget!$C$28,Budget!$I$28/Budget!$D$28,IF(A19<=Budget!$C$29,Budget!$I$29/Budget!$D$29,Budget!$I$30/Budget!$D$30)) -> 1050 | E19: =IF(A19<=Budget!$C$28,Budget!$J$28/Budget!$D$28,IF(A19<=Budget!$C$29,Budget!$J$29/Budget!$D$29,Budget!$J$30/Budget!$D$30)) -> 1140 | F19: =SUM(C19:E19) -> 5510 | G19: =SUM($F$4:F19) -> 126730 | H19: =ROUND(Budget!$B$4+Budget!$B$5+(Budget!$B$11-Budget!$B$4-Budget!$B$5)*G19/Budget!$F$11,0) -> 205 | I19: Last call: V10 + S5 countdowns | J19: 3-day reminder email
A20: 46320 | B20: =IF(A20<=Budget!$C$28,"Test",IF(A20<=Budget!$C$29,"Scale","Last call")) -> Last call | C20: =IF(A20<=Budget!$C$28,Budget!$H$28/Budget!$D$28,IF(A20<=Budget!$C$29,Budget!$H$29/Budget!$D$29,Budget!$H$30/Budget!$D$30)) -> 3320 | D20: =IF(A20<=Budget!$C$28,Budget!$I$28/Budget!$D$28,IF(A20<=Budget!$C$29,Budget!$I$29/Budget!$D$29,Budget!$I$30/Budget!$D$30)) -> 1050 | E20: =IF(A20<=Budget!$C$28,Budget!$J$28/Budget!$D$28,IF(A20<=Budget!$C$29,Budget!$J$29/Budget!$D$29,Budget!$J$30/Budget!$D$30)) -> 1140 | F20: =SUM(C20:E20) -> 5510 | G20: =SUM($F$4:F20) -> 132240 | H20: =ROUND(Budget!$B$4+Budget!$B$5+(Budget!$B$11-Budget!$B$4-Budget!$B$5)*G20/Budget!$F$11,0) -> 212
A21: 46321 | B21: =IF(A21<=Budget!$C$28,"Test",IF(A21<=Budget!$C$29,"Scale","Last call")) -> Last call | C21: =IF(A21<=Budget!$C$28,Budget!$H$28/Budget!$D$28,IF(A21<=Budget!$C$29,Budget!$H$29/Budget!$D$29,Budget!$H$30/Budget!$D$30)) -> 3320 | D21: =IF(A21<=Budget!$C$28,Budget!$I$28/Budget!$D$28,IF(A21<=Budget!$C$29,Budget!$I$29/Budget!$D$29,Budget!$I$30/Budget!$D$30)) -> 1050 | E21: =IF(A21<=Budget!$C$28,Budget!$J$28/Budget!$D$28,IF(A21<=Budget!$C$29,Budget!$J$29/Budget!$D$29,Budget!$J$30/Budget!$D$30)) -> 1140 | F21: =SUM(C21:E21) -> 5510 | G21: =SUM($F$4:F21) -> 137750 | H21: =ROUND(Budget!$B$4+Budget!$B$5+(Budget!$B$11-Budget!$B$4-Budget!$B$5)*G21/Budget!$F$11,0) -> 220 | I21: Ads stop at 11:59 PM | J21: Monday update to CEO; 1-day reminder
A22: Total | C22: =SUM(C4:C21) -> 83000 | D22: =SUM(D4:D21) -> 26250 | E22: =SUM(E4:E21) -> 28500 | F22: =SUM(F4:F21) -> 137750 | G22: =IF(ABS(F22-Budget!F11)<1,"Matches Budget","Check") -> Matches Budget | H22: =H21 -> 220
A24: Registrations by today assumes the 30 own-channel sign-ups arrive in week 1 and paid sign-ups follow spend. If you're 20% behind on any day, add budget to the best ad set and send an extra email.

Sheet Timeline
A1: Timeline: webinar Tue 27-Oct-2026, 4:00–5:00 PM IST (backup Wed 28-Oct)
A2: Updated 4-Oct. Ads now start Fri 9-Oct because the VSL and videos aren't recorded yet (Checklist row 26).
A3: When | B3: What | C3: Owner
A4: Sun 4-Oct | B4: Plan updated: 200 registrations, mass audience, VSL funnel, Meta + YouTube + Google | C4: Shourya
A5: Mon 5-Oct | B5: CEO approves budget, benefits, LinkedIn pause and email rule (Decisions 3, 4, 10–13) | C5: CEO
A6: Mon 5 / Tue 6-Oct | B6: 2-hour shoot: VSL, CTO 30s, CEO 30s, whiteboard, podcast clip (Creatives tab) | C6: CEO + CTO
A7: Wed 7-Oct | B7: Statics, carousels and Google ads ready; landing page with form and tracking live and tested | C7: Shourya + designer
A8: Thu 8-Oct | B8: VSL and first 4 videos edited; invite to own email list + WhatsApp; CEO/CTO LinkedIn posts | C8: Shourya + editor
A9: Fri 9-Oct | B9: Paid ads start: test stage (10 creatives) | C9: Shourya
A10: Tue 13-Oct | B10: Test results reviewed with CEO; scale budget released or held | C10: CEO + Shourya
A11: Wed 14-Oct | B11: Scale stage starts; retargeting on; creative refresh 1 | C11: Shourya
A12: Sun 18 / Wed 21-Oct | B12: Creative refresh 2 and 3 | C12: Shourya + editor
A13: Fri 23-Oct | B13: Full mock call: deck, timing, audio, screen share, Q&A | C13: CEO + CTO + Shourya
A14: Sat 24-Oct | B14: Last call: countdown creatives, 3-day reminder | C14: Shourya
... A18: By Mon 2-Nov | B18: Post-mortem: real cost per registration, show-up rate, meetings booked | C18: Shourya
B21: phase wise presenattion

Sheet Decisions
A1: Decisions needed from the CEO
A3: # | B3: Decision | C3: My recommendation | D3: What it unblocks | E3: CEO decision
A4: 1 | B4: Topic, title and promise | C4: Topic 2, Title A, Promise A | D4: All creative, landing page, deck example
A5: 2 | B5: Date and time | C5: Tue 27-Oct-2026, 4:00 PM IST (backup Wed 28-Oct) | D5: The whole calendar
A6: 3 | B6: Registration target | C6: ="200 registrations (pilot, mass audience) → about "&Funnel!B8&" live" -> 200 registrations (pilot, mass audience) → about 50 live | D6: Budget and daily pacing
A7: 4 | B7: Budget | C7: ="₹"&TEXT(Budget!F11,"#,##0")&" media ex-GST (₹"&TEXT(Budget!F22,"#,##0")&" all-in); release the ₹"&TEXT(Budget!F28,"#,##0")&" test budget first" -> ₹137,750 media ex-GST (₹226,125 all-in); release the ₹27,550 test budget first | D7: Campaign launch
A8: 5 | B8: Tool spend | C8: ="Zoom ₹1,580 (100 seats) + WhatsApp/email ₹5,000; expected live = "&Funnel!B8 -> Zoom ₹1,580 (100 seats) + WhatsApp/email ₹5,000; expected live = 50 | D8: Registration and reminders
A9: 6 | B9: IT-services employees in the audience? | C9: Leave them out of paid ads; allow organic sign-ups | D9: Targeting set-up
A10: 7 | B10: Speakers | C10: Confirmed once the topic is picked | D10: Landing page, video shoot
A11: 8 | B11: Sales owner for follow-up | C11: One named person, calls within 48 hours | D11: Follow-up sequence
A12: 9 | B12: One-off or a series? | C12: A series, “Think Like a CTO” | D12: Reusable pages and lists
A13: 10 | B13: Paid LinkedIn for the pilot? | C13: Pause. At ₹2,500 per registration it doesn't fit a mass target. Use CEO/CTO posts instead. | D13: Budget split
A14: 11 | B14: Business email only? | C14: For the pilot, accept any email but ask for the company name. Business-only would cut registrations roughly in half. | D14: Form set-up, volume
A15: 12 | B15: Registration benefits | C15: Approve the Benefits tab, including the ₹20,000 lucky draw and 10 free 1:1 review slots | D15: Ads, VSL, landing page
A16: 13 | B16: Creative production | C16: ="Approve ₹"&TEXT(Creatives!F38,"#,##0")&" and a 2-hour CEO + CTO shoot on Mon 5 or Tue 6 Oct" -> Approve ₹37,000 and a 2-hour CEO + CTO shoot on Mon 5 or Tue 6 Oct | D16: All ads and the VSL
A18: Green = changed or added on 4-Oct.

Sheet Checklist
A1: Execution checklist
A2: Done: | B2: =COUNTIF(D4:D59,"Done")&" of "&COUNTA(B4:B59) -> 3 of 56
A3: Area | B3: Item | C3: Owner | D3: Status
A4: Topic and content | B4: Topic, title and promise statement locked | C4: CEO | D4: In progress
A5: Topic and content | B5: Speakers confirmed for the chosen topic | C5: CEO | D5: In progress
A6: Topic and content | B6: Deck adapted and trimmed to 45 minutes | C6: CTO | D6: Not started
A7: Topic and content | B7: Worked example chosen and cleared for sharing | C7: CTO | D7: Not started
A8: Topic and content | B8: 15 minutes of Q&A kept in the runtime | C8: CTO | D8: Not started
A9: Topic and content | B9: Live poll questions written | C9: Shourya | D9: Not started
A10: Audience and targeting | B10: Job title list and experience band (10–15 years) approved | C10: Shourya | D10: Done
A11: Audience and targeting | B11: Decision taken on IT-services companies | C11: CEO | D11: Done
A12: Audience and targeting | B12: Exclusion lists built: competitors, existing clients, students, job seekers | C12: Shourya | D12: Done
A13: Audience and targeting | B13: Own email list cleaned and segmented | C13: Shourya | D13: Not started
A14: Audience and targeting | B14: Meta targeting built with AND logic (titles AND interests) | C14: Shourya | D14: Not started
... A59: Registration and data | B59: Form updated: any email + company name + question box | C59: Shourya | D59: Not started
