Workbook

Sheet CEO Summary
A1: Zarthi webinar: 200 live attendees from Google, Meta and LinkedIn ads only
A2: One-page summary for the CEO. All numbers update automatically from the Inputs tab.
A4: The answer in 5 numbers
A5: People who attend LIVE (goal) | B5: =Funnel!B8 -> 200
A6: Registrations we must buy with ads | B6: =Funnel!B7 -> 800
A7: Total budget, everything included | B7: ='Channel Plan'!E21 -> 594120
A8: Cost per live attendee | B8: ='Channel Plan'!E22 -> 2970.6
A9: Time needed | B9: 7 weeks (1 setup + 5 ads + live day + 1 follow-up)
A10: Total budget in lakh | B10: ='Channel Plan'!E21/100000 -> 5.9412
A12: Where the money goes
A13: Platform | B13: Registrations | C13: Ad spend (₹) | D13: Cost per registration (₹) | E13: % of ad spend | F13: Its job
A14: Meta | B14: ='Channel Plan'!C28 -> 480 | C14: ='Channel Plan'!E28 -> 117000 | D14: ='Channel Plan'!D28 -> 243.75 | E14: ='Channel Plan'!H28 -> 0.27272727 | F14: Volume: cheapest registrations, mixed quality
A15: LinkedIn | B15: ='Channel Plan'!C29 -> 160 | C15: ='Channel Plan'!E29 -> 208000 | D15: ='Channel Plan'!D29 -> 1300 | E15: ='Channel Plan'!H29 -> 0.48484848 | F15: Quality: reaches the exact job titles we want
A16: Google | B16: ='Channel Plan'!C30 -> 160 | C16: ='Channel Plan'!E30 -> 104000 | D16: ='Channel Plan'!D30 -> 650 | E16: ='Channel Plan'!H30 -> 0.24242424 | F16: Intent: people already searching cloud cost topics
A17: Total ad spend | B17: =SUM(B14:B16) -> 800 | C17: =SUM(C14:C16) -> 429000 | D17: =IFERROR(C17/B17,0) -> 536.25 | E17: =SUM(E14:E16) -> 1
A18: + GST, test buffer, tools, lucky draw | C18: ='Channel Plan'!E21-C17 -> 165120
A19: Total budget | C19: =C17+C18 -> 594120
A21: How it works, in 4 steps
A22: 1. Week 1 TEST: run small budgets on many ads to learn the real cost per registration on each platform.
A23: 2. Weeks 2–4 SCALE: stop the losers and put the money on the winning ads and audiences.
A24: 3. Week 5 FINAL PUSH: countdown ads and 8 reminders by email, WhatsApp and phone so registrants actually show up.
A25: 4. Live day + Week 6: run the webinar, then offer a free cloud cost assessment and hand warm leads to sales within 72 hours.
A27: Being realistic: the 3 biggest risks
A28: 1. Show-up: people from ads forget. At 20% show-up instead of 25% we need ~1,000 registrations and more budget (see the What-If tab).
A29: 2. Costs are estimates: this is the first webinar, so costs are based on industry benchmarks. Week 1 gives our real numbers and we update this file.
A30: 3. Meta brings volume but some low-quality sign-ups. LinkedIn keeps the audience senior. We check audience quality daily.
A32: Decisions needed from the CEO to start
A33: ☐ Approve the total budget shown above
A34: ☐ Pick the webinar date and time (at least 7 weeks from approval)
... A38: ☐ Define "200": peak live viewers at one time or total unique people who joined

Sheet Inputs
A1: Inputs: change the yellow cells, everything else updates
A2: Blue text on yellow = an assumption you can edit. Black = formula. Green = pulled from another tab.
A4: A. Goal and show-up
A5: Assumption | B5: Value | G5: Why this number (source / logic)
A6: Target: people who attend LIVE | B6: 200 | G6: Your goal. Decide with the CEO whether 200 means peak concurrent viewers or total unique joiners (this plan uses total unique joiners).
A7: Show-up rate (registered → attend live) | B7: 0.25 | G7: Industry median is 41.6% and the bottom quarter is 28.4% (analysis of 12,400 B2B webinars, 2026). Cold paid-ad traffic shows up less, so we plan at 25%.
A8: Stay till the end (of live attendees) | B8: 0.65 | G8: Planning estimate for a 60-min session with the live bill teardown at the end.
A9: Book a free assessment (of those who stayed) | B9: 0.12 | G9: Planning estimate for a first webinar. Replace with real data afterwards.
A10: GST on ad spend | B10: 0.18 | G10: 18% GST on Indian invoices from Meta, LinkedIn and Google.
A11: Test buffer (% of ad spend) | B11: 0.1 | G11: Money spent on ads that lose in test week. This is the price of learning real costs.
A12: Webinar platform licence, 500 seats (₹) | B12: 15000 | G12: Estimate for one month of a 500-seat plan. Confirm with a quote.
A13: Reminder tools: email + WhatsApp API (₹) | B13: 10000 | G13: Estimate for ~800 contacts × 8 reminders. Confirm with a quote.
A14: Lucky draw for people who stay till the end (₹) | B14: 20000 | G14: 10 × ₹1,000 + 2 × ₹5,000 vouchers. Optional: set to 0 to remove. Helps show-up.
A17: B. Campaign assumptions (only Google, Meta and LinkedIn ads)
A18: Campaign | B18: Platform | C18: Share of registrations | D18: Cost per registration (₹) | E18: Click-through rate (CTR) | F18: Form / page conversion | G18: Why this number (source / logic)
A19: Meta: new audience (FB + Instagram) | B19: Meta | C19: 0.525 | D19: 250 | E19: 0.01 | F19: 0.12 | G19: Volume engine. Cheapest registrations but lower quality. ₹250 is a planning estimate for India B2B webinar lead forms; test week gives the real number.
A20: Meta: retargeting (visited page / watched video) | B20: Meta | C20: 0.075 | D20: 200 | E20: 0.015 | F20: 0.2 | G20: People who already showed interest. Small but cheap. Planning estimate.
A21: LinkedIn: job-title targeting (Lead Gen Form) | B21: LinkedIn | C21: 0.2 | D21: 1300 | E21: 0.006 | F21: 0.12 | G21: Quality engine: right job titles. LinkedIn India cost per lead is ₹850–₹2,500 (2026 benchmark); we plan mid-range.
A22: Google: Search (people searching the topic) | B22: Google | C22: 0.1 | D22: 800 | E22: 0.04 | F22: 0.15 | G22: High intent but limited search volume in India for these keywords. Planning estimate.
A23: Google: YouTube video ads | B23: Google | C23: 0.1 | D23: 500 | E23: 0.008 | F23: 0.1 | G23: CTO video shown to people searching cloud cost / AWS topics. Planning estimate.
A24: Total (must be 100%) | C24: =SUM(C19:C23) -> 1 | D24: =IF(ROUND(C24,4)=1,"OK","Fix: shares must add to 100%") -> OK
A27: C. How ad money is spread over the 5 ad weeks
A28: Week | B28: What happens | C28: % of ad spend | G28: Why
A29: Week 1 | B29: TEST | C29: 0.1 | G29: Small budget, many ad versions. Find which ads and audiences give the cheapest registrations.
A30: Week 2 | B30: SCALE | C30: 0.2 | G30: Move money to winners. Raise budget on winners by ~20% every 3 days.
A31: Week 3 | B31: SCALE | C31: 0.25 | G31: Full speed on winners. Retargeting now has enough visitors.
A32: Week 4 | B32: SCALE | C32: 0.25 | G32: Full speed. Fresh ad versions to avoid fatigue.
A33: Week 5 | B33: FINAL PUSH | C33: 0.2 | G33: Countdown ads. People who register in the last 10 days show up the most.
A34: Total (must be 100%) | C34: =SUM(C29:C33) -> 1 | D34: =IF(ROUND(C34,4)=1,"OK","Fix: weeks must add to 100%") -> OK

Sheet Funnel
A1: Reverse funnel: how many people we need at each step
A2: Start from 200 live attendees and work backwards. All numbers are formulas.
A4: Step | B4: People | C4: % moving to this step | D4: What it means
A5: 1. See the ad (impressions) | B5: ='Channel Plan'!G10 -> 705492 | D5: Total ad views needed across Google, Meta and LinkedIn.
A6: 2. Click the ad | B6: ='Channel Plan'!F10 -> 6466 | C6: =IFERROR(B6/B5,0) -> 0.009165235 | D6: People who click through to the form or landing page.
A7: 3. Register | B7: =ROUNDUP(Inputs!B6/Inputs!B7,0) -> 800 | C7: =IFERROR(B7/B6,0) -> 0.1237241 | D7: To get 200 live at a 25% show-up rate we need this many registrations.
A8: 4. Attend LIVE (the goal) | B8: =ROUND(B7*Inputs!B7,0) -> 200 | C8: =IFERROR(B8/B7,0) -> 0.25 | D8: This is the 200.
A9: 5. Stay till the end | B9: =ROUND(B8*Inputs!B8,0) -> 130 | C9: =IFERROR(B9/B8,0) -> 0.65 | D9: These people see the offer and the lucky draw.
A10: 6. Book a free assessment / meeting | B10: =ROUND(B9*Inputs!B9,0) -> 16 | C10: =IFERROR(B10/B9,0) -> 0.12307692 | D10: Sales pipeline created by the webinar.
A13: In one line: about 1 in 4 people who register actually attend, so 200 live needs about 800 registrations, all bought through ads.

Sheet Channel Plan
A1: Channel plan and full budget
A2: Registrations, ad spend, clicks and impressions per campaign. Edit assumptions on the Inputs tab.
A4: Campaign | B4: Platform | C4: Registrations | D4: Cost per registration (₹) | E4: Ad spend (₹) | F4: Clicks needed | G4: Impressions needed | H4: % of ad spend
A5: =Inputs!A19 -> Meta: new audience (FB + Instagram) | B5: =Inputs!B19 -> Meta | C5: =ROUND(Inputs!C19*Funnel!$B$7,0) -> 420 | D5: =Inputs!D19 -> 250 | E5: =C5*D5 -> 105000 | F5: =IFERROR(ROUND(C5/Inputs!F19,0),0) -> 3500 | G5: =IFERROR(ROUND(F5/Inputs!E19,0),0) -> 350000 | H5: =IFERROR(E5/$E$10,0) -> 0.24475524
A6: =Inputs!A20 -> Meta: retargeting (visited page / watched video) | B6: =Inputs!B20 -> Meta | C6: =ROUND(Inputs!C20*Funnel!$B$7,0) -> 60 | D6: =Inputs!D20 -> 200 | E6: =C6*D6 -> 12000 | F6: =IFERROR(ROUND(C6/Inputs!F20,0),0) -> 300 | G6: =IFERROR(ROUND(F6/Inputs!E20,0),0) -> 20000 | H6: =IFERROR(E6/$E$10,0) -> 0.027972028
A7: =Inputs!A21 -> LinkedIn: job-title targeting (Lead Gen Form) | B7: =Inputs!B21 -> LinkedIn | C7: =ROUND(Inputs!C21*Funnel!$B$7,0) -> 160 | D7: =Inputs!D21 -> 1300 | E7: =C7*D7 -> 208000 | F7: =IFERROR(ROUND(C7/Inputs!F21,0),0) -> 1333 | G7: =IFERROR(ROUND(F7/Inputs!E21,0),0) -> 222167 | H7: =IFERROR(E7/$E$10,0) -> 0.48484848
A8: =Inputs!A22 -> Google: Search (people searching the topic) | B8: =Inputs!B22 -> Google | C8: =ROUND(Inputs!C22*Funnel!$B$7,0) -> 80 | D8: =Inputs!D22 -> 800 | E8: =C8*D8 -> 64000 | F8: =IFERROR(ROUND(C8/Inputs!F22,0),0) -> 533 | G8: =IFERROR(ROUND(F8/Inputs!E22,0),0) -> 13325 | H8: =IFERROR(E8/$E$10,0) -> 0.14918415
A9: =Inputs!A23 -> Google: YouTube video ads | B9: =Inputs!B23 -> Google | C9: =ROUND(Inputs!C23*Funnel!$B$7,0) -> 80 | D9: =Inputs!D23 -> 500 | E9: =C9*D9 -> 40000 | F9: =IFERROR(ROUND(C9/Inputs!F23,0),0) -> 800 | G9: =IFERROR(ROUND(F9/Inputs!E23,0),0) -> 100000 | H9: =IFERROR(E9/$E$10,0) -> 0.093240093
A10: Total | C10: =SUM(C5:C9) -> 800 | D10: =IFERROR(E10/C10,0) -> 536.25 | E10: =SUM(E5:E9) -> 429000 | F10: =SUM(F5:F9) -> 6466 | G10: =SUM(G5:G9) -> 705492 | H10: =SUM(H5:H9) -> 1
A11: Cost per registration in the Total row is the blended average across all campaigns.
A13: Full budget (everything included)
A14: Item | E14: Amount (₹) | H14: % of total
A15: Ad spend: Google + Meta + LinkedIn | E15: =E10 -> 429000 | H15: =IFERROR(E15/$E$21,0) -> 0.72207635
A16: GST on ad spend | E16: =E10*Inputs!B10 -> 77220 | H16: =IFERROR(E16/$E$21,0) -> 0.12997374
A17: Test buffer (ads that lose in week 1) | E17: =E10*Inputs!B11 -> 42900 | H17: =IFERROR(E17/$E$21,0) -> 0.072207635
A18: Webinar platform licence | E18: =Inputs!B12 -> 15000 | H18: =IFERROR(E18/$E$21,0) -> 0.025247425
A19: Reminder tools (email + WhatsApp) | E19: =Inputs!B13 -> 10000 | H19: =IFERROR(E19/$E$21,0) -> 0.016831617
A20: Lucky draw (optional) | E20: =Inputs!B14 -> 20000 | H20: =IFERROR(E20/$E$21,0) -> 0.033663233
A21: TOTAL BUDGET (all-in) | E21: =SUM(E15:E20) -> 594120 | H21: =SUM(H15:H20) -> 1
A22: Cost per LIVE attendee (all-in) | E22: =IFERROR(E21/Funnel!B8,0) -> 2970.6
A23: Cost per registration (all-in) | E23: =IFERROR(E21/C10,0) -> 742.65
A26: By platform
A27: Platform | C27: Registrations | D27: Cost per registration (₹) | E27: Ad spend (₹) | H27: % of ad spend
A28: Meta | C28: =SUMIF($B$5:$B$9,A28,$C$5:$C$9) -> 480 | D28: =IFERROR(E28/C28,0) -> 243.75 | E28: =SUMIF($B$5:$B$9,A28,$E$5:$E$9) -> 117000 | H28: =IFERROR(E28/$E$10,0) -> 0.27272727
A29: LinkedIn | C29: =SUMIF($B$5:$B$9,A29,$C$5:$C$9) -> 160 | D29: =IFERROR(E29/C29,0) -> 1300 | E29: =SUMIF($B$5:$B$9,A29,$E$5:$E$9) -> 208000 | H29: =IFERROR(E29/$E$10,0) -> 0.48484848
A30: Google | C30: =SUMIF($B$5:$B$9,A30,$C$5:$C$9) -> 160 | D30: =IFERROR(E30/C30,0) -> 650 | E30: =SUMIF($B$5:$B$9,A30,$E$5:$E$9) -> 104000 | H30: =IFERROR(E30/$E$10,0) -> 0.24242424
A31: Total | C31: =SUM(C28:C30) -> 800 | D31: =IFERROR(E31/C31,0) -> 536.25 | E31: =SUM(E28:E30) -> 429000 | H31: =SUM(H28:H30) -> 1

Sheet Weekly Plan
A1: Week-by-week plan: money, registrations and checkpoints
A2: Ads run 5 weeks. Week 0 is setup, Week 6 is follow-up. Weekly % split is on the Inputs tab.
A4: Week | B4: Stage | C4: Meta (₹) | D4: LinkedIn (₹) | E4: Google (₹) | F4: Total ad spend (₹) | G4: Daily spend (₹) | H4: New registrations (target) | I4: Total registrations so far | J4: % of goal reached | K4: Main jobs this week
A5: Week 0 | B5: SETUP | C5: 0 | D5: 0 | E5: 0 | F5: 0 | G5: 0 | H5: 0 | I5: 0 | J5: 0 | K5: Lock title and date. Build landing page. Install Meta pixel, LinkedIn Insight Tag, Google tag + UTMs. Shoot CEO/CTO videos. Make 10–12 ads. Book webinar platform.
A6: =Inputs!A29 -> Week 1 | B6: =Inputs!B29 -> TEST | C6: ='Channel Plan'!$E$28*Inputs!$C29 -> 11700 | D6: ='Channel Plan'!$E$29*Inputs!$C29 -> 20800 | E6: ='Channel Plan'!$E$30*Inputs!$C29 -> 10400 | F6: =SUM(C6:E6) -> 42900 | G6: =F6/7 -> 6128.5714 | H6: =ROUND('Channel Plan'!$C$10*Inputs!$C29,0) -> 80 | I6: =SUM($H$6:H6) -> 80 | J6: =IFERROR(I6/'Channel Plan'!$C$10,0) -> 0.1 | K6: Run 3 hooks × 3 audiences on Meta, 2 × 2 on LinkedIn, 2 ad groups on Google. Check cost per registration daily.
A7: =Inputs!A30 -> Week 2 | B7: =Inputs!B30 -> SCALE | C7: ='Channel Plan'!$E$28*Inputs!$C30 -> 23400 | D7: ='Channel Plan'!$E$29*Inputs!$C30 -> 41600 | E7: ='Channel Plan'!$E$30*Inputs!$C30 -> 20800 | F7: =SUM(C7:E7) -> 85800 | G7: =F7/7 -> 12257.143 | H7: =ROUND('Channel Plan'!$C$10*Inputs!$C30,0) -> 160 | I7: =SUM($H$6:H7) -> 240 | J7: =IFERROR(I7/'Channel Plan'!$C$10,0) -> 0.3 | K7: Switch off losing ads. Put money on winners. Turn on retargeting.
A8: =Inputs!A31 -> Week 3 | B8: =Inputs!B31 -> SCALE | C8: ='Channel Plan'!$E$28*Inputs!$C31 -> 29250 | D8: ='Channel Plan'!$E$29*Inputs!$C31 -> 52000 | E8: ='Channel Plan'!$E$30*Inputs!$C31 -> 26000 | F8: =SUM(C8:E8) -> 107250 | G8: =F8/7 -> 15321.429 | H8: =ROUND('Channel Plan'!$C$10*Inputs!$C31,0) -> 200 | I8: =SUM($H$6:H8) -> 440 | J8: =IFERROR(I8/'Channel Plan'!$C$10,0) -> 0.55 | K8: Scale winners. Add 2 new ad versions. Monday update to CEO.
A9: =Inputs!A32 -> Week 4 | B9: =Inputs!B32 -> SCALE | C9: ='Channel Plan'!$E$28*Inputs!$C32 -> 29250 | D9: ='Channel Plan'!$E$29*Inputs!$C32 -> 52000 | E9: ='Channel Plan'!$E$30*Inputs!$C32 -> 26000 | F9: =SUM(C9:E9) -> 107250 | G9: =F9/7 -> 15321.429 | H9: =ROUND('Channel Plan'!$C$10*Inputs!$C32,0) -> 200 | I9: =SUM($H$6:H9) -> 640 | J9: =IFERROR(I9/'Channel Plan'!$C$10,0) -> 0.8 | K9: Scale winners. Refresh tired ads (CTR falling). Monday update to CEO.
A10: =Inputs!A33 -> Week 5 | B10: =Inputs!B33 -> FINAL PUSH | C10: ='Channel Plan'!$E$28*Inputs!$C33 -> 23400 | D10: ='Channel Plan'!$E$29*Inputs!$C33 -> 41600 | E10: ='Channel Plan'!$E$30*Inputs!$C33 -> 20800 | F10: =SUM(C10:E10) -> 85800 | G10: =F10/7 -> 12257.143 | H10: =ROUND('Channel Plan'!$C$10*Inputs!$C33,0) -> 160 | I10: =SUM($H$6:H10) -> 800 | J10: =IFERROR(I10/'Channel Plan'!$C$10,0) -> 1 | K10: Countdown ads (7 days / tomorrow / today). Reminder sequence running. Platform test call.
A11: LIVE DAY | B11: WEBINAR | I11: =Funnel!B8 -> 200 | K11: Tue/Wed/Thu, 4–5 pm IST. 60 minutes. Backup host ready.
A12: Week 6 | B12: FOLLOW-UP | C12: 0 | D12: 0 | E12: 0 | F12: 0 | G12: 0 | H12: 0 | I12: 0 | J12: 0 | K12: Same evening: assessment booking email. Recording to no-shows. Sales calls within 72 hours. Results review in 5 days.
A13: Total | C13: =SUM(C6:C10) -> 117000 | D13: =SUM(D6:D10) -> 208000 | E13: =SUM(E6:E10) -> 104000 | F13: =SUM(F6:F10) -> 429000 | H13: =SUM(H6:H10) -> 800
A15: Checkpoint rule: if 'Total registrations so far' is more than 20% behind target at the end of any week, use the test buffer to add budget to the best campaign and refresh ads.

Sheet Targeting & Ads
A1: Who we target and what ads we run
A2: One row per campaign. Copy this into the ad accounts at setup.
A4: Campaign | B4: Who sees the ad (targeting) | C4: Ad format | D4: Ad message / hook | E4: Where the click goes
A5: Meta: new audience (FB + Instagram) | B5: India metros (Bengaluru, Mumbai, Delhi NCR, Hyderabad, Pune, Chennai). Age 25–50. Interests: cloud computing, AWS, Microsoft Azure, DevOps, IT management. Exclude students/job seekers where possible. | C5: 30-sec CTO talking-head video, 15-sec text reel, speaker card image, 5-slide carousel | D5: "Your cloud bill keeps growing but traffic doesn't? Watch a CTO tear down real cloud bills, live." | E5: Meta instant lead form (pre-filled) AND landing page: test both in week 1
A6: Meta: retargeting | B6: People who visited the landing page but did not register, watched 50%+ of a video, or opened the lead form without submitting. Last 30 days. | C6: Countdown images (7 days / tomorrow / today), "X people registered" image | D6: "Seats are filling. Live teardown of real cloud bills: [date], 4 pm." | E6: Landing page
A7: LinkedIn: job-title targeting | B7: India. Job titles: IT Manager, Engineering Manager, Head of IT, Tech Lead, Cloud Architect, DevOps Manager, CTO, VP Engineering. Company size 200+. Exclude your own employees and competitors. | C7: Single image (speaker card), document ad (5 CTO questions), 30-sec video. Thought Leader Ads from CEO/CTO posts if approved | D7: "Your cloud bill is a leadership problem. The CTO decision framework, live, with real bill teardowns." | E7: LinkedIn Lead Gen Form (pre-filled, 5 fields max)
A8: Google: Search | B8: India. Keywords: cloud cost optimization, reduce AWS bill, AWS cost reduction, cloud migration strategy, Azure cost management. Phrase + exact match. Negative keywords: jobs, course, free, certification, salary. | C8: Responsive search ads, 3 ad groups by keyword theme. Sitelinks: Agenda, Speakers, Register. | D8: "Free Live Webinar: Cut Your Cloud Bill | CTO Framework + Live Bill Teardown" | E8: Landing page
A9: Google: YouTube video ads | B9: India. Custom segment: people who searched cloud cost / AWS / Azure terms. Placements on tech and cloud channels. | C9: 60-sec mini-lesson video (skippable in-stream) + 15-sec Shorts version | D9: Give one part of the framework for free, "the rest is live on [date]" | E9: Landing page
A11: Landing page / form checklist (everything on the first screen)
A12: 1. Headline = webinar title. Sub-headline = the live cloud bill teardown promise.
A13: 2. Photos of CEO and CTO with a 2-line bio and client names (with permission).
A14: 3. Three bullets: what you will take away.
A15: 4. Form with only 5 fields: name, work email, phone, job title, monthly cloud bill (dropdown).
A16: 5. Thank-you page: Add to Calendar button, WhatsApp opt-in, invite-a-colleague link.
A17: 6. Clearly say: "No product demo. No sales pitch."

Sheet Show-up Plan
A1: Show-up plan: turning registrations into live attendees
A2: Ads bring registrations. These reminders (no ad cost) decide whether we hit 200 live.
A4: When | B4: Channel | C4: Message
A5: Right after registering | B5: Email + WhatsApp | C5: Confirmation + calendar invite (.ics) + link to send your cloud bill question
A6: 7 days before | B6: Email | C6: Value teaser: one part of the framework, "full version live"
A7: 3 days before | B7: Email | C7: Agenda + "bills for the live teardown are being chosen"
A8: 1 day before | B8: Email + WhatsApp | C8: Reminder for tomorrow + lucky draw for those who stay till the end
A9: 1 day before | B9: Sales team phone call | C9: Personal call to the top 50 best-fit registrants (big cloud bill)
A10: 2 hours before | B10: WhatsApp | C10: Join link
A11: 15 minutes before | B11: Email + WhatsApp | C11: "We are going live"
A12: 5 minutes after start | B12: Email + WhatsApp | C12: To no-shows: "We have started, the teardown is at the end"
A14: Rules: use the same join link in every reminder. Do NOT promise a recording in advance (it lowers live attendance). Send the recording to no-shows after.

Sheet Rules
A1: Daily rules: when to stop an ad and when to add money
A2: Check ads every day. Change ads twice a week. Send the registration count to the CEO every Monday.
A4: What we watch | B4: Good (target) | C4: Stop / alarm | D4: What we do
A5: Meta cost per registration | B5: Below ₹250 | C5: Above ₹450 after ₹2,000 spent | D5: Stop that ad, move money to the winner
A6: LinkedIn cost per registration | B6: Below ₹1,300 | C6: Above ₹2,000 after ₹5,000 spent | D6: Stop that ad, change audience or image
A7: Google Search cost per registration | B7: Below ₹800 | C7: Above ₹1,400 after ₹4,000 spent | D7: Pause keyword, add negative keywords
A8: YouTube cost per registration | B8: Below ₹500 | C8: Above ₹900 after ₹3,000 spent | D8: Change the first 5 seconds of the video
A9: Landing page conversion | B9: Above 12% | C9: Below 8% | D9: Change headline or shorten the form
A10: Right audience (manager+ title and bill filled) | B10: Above 50% | C10: Below 35% | D10: Tighten Meta interests, shift money to LinkedIn
A11: Winning ad | B11: Cost 30% below target | D11: Raise budget 20% every 3 days
A12: Ad fatigue (CTR drops 30% from its best) | C12: CTR falls 30% | D12: Swap in a new ad version
A13: Show-up rate on the day | B13: Above 25% | D13: Learning for the next webinar

Sheet What-If
A1: What-if: what happens if things go better or worse
A2: Total all-in budget for 200 live attendees, depending on show-up rate and ad costs. Edit the blue headers to test other values.
A4: Total budget (₹, all-in) for 200 live attendees
A5: Show-up rate ↓ / Ad cost change → | B5: -0.2 | C5: 0 | D5: 0.2 | E5: 0.4
A6: 0.2 | B6: =ROUNDUP(Inputs!$B$6/$A6,0)*'Channel Plan'!$D$10*(1+B$5)*(1+Inputs!$B$10+Inputs!$B$11)+Inputs!$B$12+Inputs!$B$13+Inputs!$B$14 -> 594120 | C6: =ROUNDUP(Inputs!$B$6/$A6,0)*'Channel Plan'!$D$10*(1+C$5)*(1+Inputs!$B$10+Inputs!$B$11)+Inputs!$B$12+Inputs!$B$13+Inputs!$B$14 -> 731400 | D6: =ROUNDUP(Inputs!$B$6/$A6,0)*'Channel Plan'!$D$10*(1+D$5)*(1+Inputs!$B$10+Inputs!$B$11)+Inputs!$B$12+Inputs!$B$13+Inputs!$B$14 -> 868680 | E6: =ROUNDUP(Inputs!$B$6/$A6,0)*'Channel Plan'!$D$10*(1+E$5)*(1+Inputs!$B$10+Inputs!$B$11)+Inputs!$B$12+Inputs!$B$13+Inputs!$B$14 -> 1005960
A7: 0.25 | B7: =ROUNDUP(Inputs!$B$6/$A7,0)*'Channel Plan'!$D$10*(1+B$5)*(1+Inputs!$B$10+Inputs!$B$11)+Inputs!$B$12+Inputs!$B$13+Inputs!$B$14 -> 484296 | C7: =ROUNDUP(Inputs!$B$6/$A7,0)*'Channel Plan'!$D$10*(1+C$5)*(1+Inputs!$B$10+Inputs!$B$11)+Inputs!$B$12+Inputs!$B$13+Inputs!$B$14 -> 594120 | D7: =ROUNDUP(Inputs!$B$6/$A7,0)*'Channel Plan'!$D$10*(1+D$5)*(1+Inputs!$B$10+Inputs!$B$11)+Inputs!$B$12+Inputs!$B$13+Inputs!$B$14 -> 703944 | E7: =ROUNDUP(Inputs!$B$6/$A7,0)*'Channel Plan'!$D$10*(1+E$5)*(1+Inputs!$B$10+Inputs!$B$11)+Inputs!$B$12+Inputs!$B$13+Inputs!$B$14 -> 813768
A8: 0.3 | B8: =ROUNDUP(Inputs!$B$6/$A8,0)*'Channel Plan'!$D$10*(1+B$5)*(1+Inputs!$B$10+Inputs!$B$11)+Inputs!$B$12+Inputs!$B$13+Inputs!$B$14 -> 411263.04 | C8: =ROUNDUP(Inputs!$B$6/$A8,0)*'Channel Plan'!$D$10*(1+C$5)*(1+Inputs!$B$10+Inputs!$B$11)+Inputs!$B$12+Inputs!$B$13+Inputs!$B$14 -> 502828.8 | D8: =ROUNDUP(Inputs!$B$6/$A8,0)*'Channel Plan'!$D$10*(1+D$5)*(1+Inputs!$B$10+Inputs!$B$11)+Inputs!$B$12+Inputs!$B$13+Inputs!$B$14 -> 594394.56 | E8: =ROUNDUP(Inputs!$B$6/$A8,0)*'Channel Plan'!$D$10*(1+E$5)*(1+Inputs!$B$10+Inputs!$B$11)+Inputs!$B$12+Inputs!$B$13+Inputs!$B$14 -> 685960.32
A9: 0.35 | B9: =ROUNDUP(Inputs!$B$6/$A9,0)*'Channel Plan'!$D$10*(1+B$5)*(1+Inputs!$B$10+Inputs!$B$11)+Inputs!$B$12+Inputs!$B$13+Inputs!$B$14 -> 359096.64 | C9: =ROUNDUP(Inputs!$B$6/$A9,0)*'Channel Plan'!$D$10*(1+C$5)*(1+Inputs!$B$10+Inputs!$B$11)+Inputs!$B$12+Inputs!$B$13+Inputs!$B$14 -> 437620.8 | D9: =ROUNDUP(Inputs!$B$6/$A9,0)*'Channel Plan'!$D$10*(1+D$5)*(1+Inputs!$B$10+Inputs!$B$11)+Inputs!$B$12+Inputs!$B$13+Inputs!$B$14 -> 516144.96 | E9: =ROUNDUP(Inputs!$B$6/$A9,0)*'Channel Plan'!$D$10*(1+E$5)*(1+Inputs!$B$10+Inputs!$B$11)+Inputs!$B$12+Inputs!$B$13+Inputs!$B$14 -> 594669.12
A10: Expected case = 25% show-up and +0% ad cost change (this matches the Channel Plan total, up to rounding).
A12: Registrations needed at each show-up rate
A13: Show-up rate | B13: Registrations needed | C13: Ad spend at expected cost (₹)
A14: =A6 -> 0.2 | B14: =ROUNDUP(Inputs!$B$6/A14,0) -> 1000 | C14: =B14*'Channel Plan'!$D$10 -> 536250
A15: =A7 -> 0.25 | B15: =ROUNDUP(Inputs!$B$6/A15,0) -> 800 | C15: =B15*'Channel Plan'!$D$10 -> 429000
A16: =A8 -> 0.3 | B16: =ROUNDUP(Inputs!$B$6/A16,0) -> 667 | C16: =B16*'Channel Plan'!$D$10 -> 357678.75
A17: =A9 -> 0.35 | B17: =ROUNDUP(Inputs!$B$6/A17,0) -> 572 | C17: =B17*'Channel Plan'!$D$10 -> 306735
A19: Takeaway: show-up rate matters as much as ad cost. Every 5 points of show-up we gain saves lakhs, which is why the reminder plan is not optional.

Sheet Glossary
A1: Glossary: plain-English meaning of every term
A4: Term | B4: Meaning
A5: Impression | B5: One time an ad is shown on someone's screen.
A6: CTR (click-through rate) | B6: Out of 100 people who see the ad, how many click. 1% = 1 in 100.
A7: Conversion rate | B7: Out of 100 people who click, how many fill the registration form.
A8: Registration | B8: Someone who filled the form. Not yet an attendee.
A9: Cost per registration (CPR) | B9: Ad money spent ÷ number of registrations.
A10: Show-up rate | B10: Out of 100 registrations, how many actually join live.
A11: Cost per live attendee | B11: Total budget ÷ number of people who attend live. The number that matters.
A12: Retargeting | B12: Showing ads again to people who already visited our page or watched our video.
A13: Lead Gen Form / Lead form | B13: A form inside LinkedIn or Meta that is pre-filled with the person's details. Higher sign-ups than a website form.
A14: Thought Leader Ad (LinkedIn) | B14: The company pays to promote a post from the CEO's or CTO's personal profile. Usually cheaper and more trusted than company-page ads.
A15: Pixel / Insight Tag / Google tag | B15: Small tracking codes on the landing page that tell each ad platform who registered, so it can find more people like them.
... A18: Ad fatigue | B18: When the same people see an ad too often and stop clicking. Fix: new ad version.
